while_machine.py
while_machine-1.0.2.dist-info/METADATA
while_machine-1.0.2.dist-info/WHEEL
while_machine-1.0.2.dist-info/top_level.txt
while_machine-1.0.2.dist-info/RECORD
